flask_restless_swagger/__init__.py
flask_restless_swagger/static/.DS_Store
flask_restless_swagger/static/swagger-ui/.DS_Store
flask_restless_swagger/static/swagger-ui/index.html
flask_restless_swagger/static/swagger-ui/o2c.html
flask_restless_swagger/static/swagger-ui/swagger-ui.js
flask_restless_swagger/static/swagger-ui/swagger-ui.min.js
flask_restless_swagger/static/swagger-ui/css/print.css
flask_restless_swagger/static/swagger-ui/css/reset.css
flask_restless_swagger/static/swagger-ui/css/screen.css
flask_restless_swagger/static/swagger-ui/css/style.css
flask_restless_swagger/static/swagger-ui/css/typography.css
flask_restless_swagger/static/swagger-ui/fonts/DroidSans-Bold.ttf
flask_restless_swagger/static/swagger-ui/fonts/DroidSans.ttf
flask_restless_swagger/static/swagger-ui/images/collapse.gif
flask_restless_swagger/static/swagger-ui/images/expand.gif
flask_restless_swagger/static/swagger-ui/images/explorer_icons.png
flask_restless_swagger/static/swagger-ui/images/favicon-16x16.png
flask_restless_swagger/static/swagger-ui/images/favicon-32x32.png
flask_restless_swagger/static/swagger-ui/images/favicon.ico
flask_restless_swagger/static/swagger-ui/images/logo_small.png
flask_restless_swagger/static/swagger-ui/images/pet_store_api.png
flask_restless_swagger/static/swagger-ui/images/throbber.gif
flask_restless_swagger/static/swagger-ui/images/wordnik_api.png
flask_restless_swagger/static/swagger-ui/lang/ca.js
flask_restless_swagger/static/swagger-ui/lang/el.js
flask_restless_swagger/static/swagger-ui/lang/en.js
flask_restless_swagger/static/swagger-ui/lang/es.js
flask_restless_swagger/static/swagger-ui/lang/fr.js
flask_restless_swagger/static/swagger-ui/lang/geo.js
flask_restless_swagger/static/swagger-ui/lang/it.js
flask_restless_swagger/static/swagger-ui/lang/ja.js
flask_restless_swagger/static/swagger-ui/lang/ko-kr.js
flask_restless_swagger/static/swagger-ui/lang/pl.js
flask_restless_swagger/static/swagger-ui/lang/pt.js
flask_restless_swagger_2-0.0.3.dist-info/DESCRIPTION.rst
flask_restless_swagger_2-0.0.3.dist-info/METADATA
flask_restless_swagger_2-0.0.3.dist-info/RECORD
flask_restless_swagger_2-0.0.3.dist-info/WHEEL
flask_restless_swagger_2-0.0.3.dist-info/metadata.json
flask_restless_swagger_2-0.0.3.dist-info/top_level.txt
