Metadata-Version: 1.1
Name: flask-restless-swagger-2
Version: 0.0.3
Summary: Magically create swagger documentation as you magically create your RESTful API
Home-page: https://github.com/lucasSimonelli/flask-restless-swagger
Author: Lucas Simonelli
Author-email: lucasp.simonelli@gmail.com
License: BSD
Keywords: flask-restless-swagger
Platform: UNKNOWN
Classifier: Development Status :: 2 - Pre-Alpha
Classifier: Intended Audience :: Developers
Classifier: License :: OSI Approved :: BSD License
Classifier: Natural Language :: English
Classifier: Programming Language :: Python :: 2
Classifier: Programming Language :: Python :: 2.6
Classifier: Programming Language :: Python :: 2.7
Classifier: Programming Language :: Python :: 3
Classifier: Programming Language :: Python :: 3.3
Classifier: Programming Language :: Python :: Implementation :: PyPy
Classifier: Topic :: Internet :: WWW/HTTP :: Dynamic Content
Classifier: Topic :: Software Development :: Libraries :: Python Modules
